setup.py
watchsubs/__init__.py
watchsubs/watchsubs.py
watchsubs.egg-info/PKG-INFO
watchsubs.egg-info/SOURCES.txt
watchsubs.egg-info/dependency_links.txt
watchsubs.egg-info/entry_points.txt
watchsubs.egg-info/requires.txt
watchsubs.egg-info/top_level.txt