Metadata-Version: 1.1
Name: watchsubs
Version: 0.1
Summary: Joint magic from watchdog and subliminal
Home-page: https://www.github.com/emanjavacas/watchsubs
Author: Enrique
Author-email: enrique.manjavacas@gmail.com
License: MIT
Download-URL: https://api.github.com/repos/emanjavacas/watchsubs/tarball
Platform: UNKNOWN
